git_autosemver/__init__.py
git_autosemver/main.py
git_autosemver-1.0.0.dist-info/DESCRIPTION.rst
git_autosemver-1.0.0.dist-info/entry_points.txt
git_autosemver-1.0.0.dist-info/METADATA
git_autosemver-1.0.0.dist-info/metadata.json
git_autosemver-1.0.0.dist-info/RECORD
git_autosemver-1.0.0.dist-info/top_level.txt
git_autosemver-1.0.0.dist-info/WHEEL
